jnprsr/__init__.py
jnprsr/anytree_custom_dict_exporter.py
jnprsr/anytree_junos_resolver.py
jnprsr/prompt_toolkit_custom_nested_completer.py
jnprsr/utils.py
jnprsr/cli/__init__.py
jnprsr/cli/cliutils.py
jnprsr/cli/merge.py
jnprsr/cli/pretty.py
jnprsr/cli/subtree.py
jnprsr/parser/JuniperAST.py
jnprsr/parser/JuniperASTRenderer.py
jnprsr/parser/JuniperLexer.py
jnprsr/parser/JuniperParser.py
jnprsr/parser/JuniperParserListener.py
jnprsr/parser/__init__.py
jnprsr-0.1.2.dist-info/licenses/LICENSE
jnprsr-0.1.2.dist-info/METADATA
jnprsr-0.1.2.dist-info/WHEEL
jnprsr-0.1.2.dist-info/entry_points.txt
jnprsr-0.1.2.dist-info/top_level.txt
jnprsr-0.1.2.dist-info/RECORD
