Metadata-Version: 2.4
Name: jnprsr
Version: 0.1.2
Summary: jnprsr is a Parser for Juniper Configuration Files
Author-email: markusju <markus.jungbluth@gmail.com>
Maintainer-email: markusju <markus.jungbluth@gmail.com>
License:                                  Apache License
Project-URL: Homepage, https://github.com/markusju/jnprsr/
Project-URL: Bug Reports, https://github.com/markusju/jnprsr/issues
Project-URL: Source, https://github.com/markusju/jnprsr/
Keywords: jnpr,juniper,parser,junos,configuration,config
Classifier: Development Status :: 4 - Beta
Classifier: Intended Audience :: Developers
Classifier: Topic :: Software Development :: Build Tools
Classifier: License :: OSI Approved :: Apache Software License
Classifier: Programming Language :: Python :: 3
Classifier: Programming Language :: Python :: 3.9
Classifier: Programming Language :: Python :: 3.10
Classifier: Programming Language :: Python :: 3.11
Classifier: Programming Language :: Python :: 3.12
Classifier: Programming Language :: Python :: 3.13
Classifier: Programming Language :: Python :: 3 :: Only
Requires-Python: >=3.9
License-File: LICENSE
Requires-Dist: antlr4-python3-runtime==4.10
Requires-Dist: argparse
Requires-Dist: typer
Requires-Dist: anytree
Requires-Dist: prompt-toolkit
Dynamic: license-file
